backvm/__init__.py
backvm/utils.py
backvm/scripts/__init__.py
backvm/scripts/backvm.py
backvm-0.4.0.dist-info/LICENSE.txt
backvm-0.4.0.dist-info/METADATA
backvm-0.4.0.dist-info/WHEEL
backvm-0.4.0.dist-info/entry_points.txt
backvm-0.4.0.dist-info/top_level.txt
backvm-0.4.0.dist-info/RECORD
