Metadata-Version: 2.1
Name: backvm
Version: 0.4.0
Summary: This program performs the backup of one or several KVM domains
Home-page: https://codeberg.org/pmarini/backvm/
Author: Pietro Marini
Author-email: backvm@fastmail.com
License: new BSD
Platform: UNKNOWN
Requires-Dist: click
Requires-Dist: libvirt-python
Requires-Dist: pandas
Requires-Dist: paramiko
Requires-Dist: scp
